dbhelper/__init__.py
dbhelper/core.py
db_helper_lib-0.2.0.dist-info/LICENSE
db_helper_lib-0.2.0.dist-info/METADATA
db_helper_lib-0.2.0.dist-info/WHEEL
db_helper_lib-0.2.0.dist-info/top_level.txt
db_helper_lib-0.2.0.dist-info/RECORD
