Metadata-Version: 2.2
Name: db_helper_lib
Version: 0.2.0
Summary: Библиотека позволяет быстро выполнять запросы к БД, а также превращать данные в JSON
Home-page: https://github.com/LostKosmonaut26/db_helper
Author: LostKosmonaut
Author-email: maxon1204@gmail.com
Classifier: Programming Language :: Python :: 3
Classifier: License :: OSI Approved :: MIT License
Classifier: Operating System :: OS Independent
Requires-Python: >=3.7
License-File: LICENSE
Requires-Dist: pyodbc
Dynamic: author
Dynamic: author-email
Dynamic: classifier
Dynamic: description
Dynamic: description-content-type
Dynamic: home-page
Dynamic: requires-dist
Dynamic: requires-python
Dynamic: summary
